artifactory/__init__.py
artifactory/api.py
artifactory/client.py
artifactory/client_config.py
artifactory/shortcuts.py
artifactory/units.py
artifactory/models/__init__.py
artifactory/models/requests.py
artifactory/models/resources.py
artifactory/models/responses.py
artifactory/models/utility.py
artifactory/utils/__init__.py
artifactory/utils/functools.py
artifactory/utils/requesters/__init__.py
artifactory/utils/requesters/base.py
artifactory/utils/requesters/default.py
artifactory_vk-0.1.2.dist-info/METADATA
artifactory_vk-0.1.2.dist-info/WHEEL
artifactory_vk-0.1.2.dist-info/top_level.txt
artifactory_vk-0.1.2.dist-info/RECORD
