Metadata-Version: 2.1
Name: artifactory-vk
Version: 0.1.2
Requires-Python: >=3.10
Requires-Dist: pydantic ~=2.8.2
Requires-Dist: requests ~=2.32.3
Requires-Dist: tuspy ~=1.0.3
